flake8_phabricator_formatter/__init__.py
flake8_phabricator_formatter/formatters.py
flake8_phabricator_formatter-0.1.1.dist-info/METADATA
flake8_phabricator_formatter-0.1.1.dist-info/WHEEL
flake8_phabricator_formatter-0.1.1.dist-info/entry_points.txt
flake8_phabricator_formatter-0.1.1.dist-info/top_level.txt
flake8_phabricator_formatter-0.1.1.dist-info/RECORD
