Metadata-Version: 2.1
Name: flake8-phabricator-formatter
Version: 0.1.1
Summary: flake8 formatter for Phabricator's Harbormaster
Home-page: https://forge.softwareheritage.org/source/flake8-phabricator-formatter/
Author: Software Heritage developers
Author-email: swh-devel@inria.fr
License: MIT
Platform: UNKNOWN
Classifier: Framework :: Flake8
Classifier: Environment :: Console
Classifier: Intended Audience :: Developers
Classifier: License :: OSI Approved :: MIT License
Classifier: Programming Language :: Python
Classifier: Programming Language :: Python :: 2
Classifier: Programming Language :: Python :: 3
Classifier: Topic :: Software Development :: Libraries :: Python Modules
Classifier: Topic :: Software Development :: Quality Assurance
Requires-Dist: flake8 (>3.0.0)
